{
    "key": "group_5cbf1a14143d3",
    "title": "Content Blocks",
    "fields": [
        {
            "key": "field_5cbf1a2d91520",
            "label": "Content Blocks",
            "name": "content_blocks",
            "type": "flexible_content",
            "instructions": "Drag and drop these blocks to rearrange the order of the content.",
            "required": 0,
            "conditional_logic": 0,
            "wrapper": {
                "width": "",
                "class": "",
                "id": ""
            },
            "layouts": {
                "layout_5cbf1a67ec9b8": {
                    "key": "layout_5cbf1a67ec9b8",
                    "name": "block_feature",
                    "label": "Feature Block",
                    "display": "block",
                    "sub_fields": [
                        {
                            "key": "field_5cbf1a8e91521",
                            "label": "Content",
                            "name": "content",
                            "type": "wysiwyg",
                            "instructions": "",
                            "required": 0,
                            "conditional_logic": 0,
                            "wrapper": {
                                "width": "",
                                "class": "",
                                "id": ""
                            },
                            "default_value": "",
                            "tabs": "all",
                            "toolbar": "full",
                            "media_upload": 1,
                            "delay": 0
                        },
                        {
                            "key": "field_5cbf1ac991523",
                            "label": "Link",
                            "name": "link",
                            "type": "link",
                            "instructions": "",
                            "required": 0,
                            "conditional_logic": 0,
                            "wrapper": {
                                "width": "",
                                "class": "",
                                "id": ""
                            },
                            "return_format": "array"
                        },
                        {
                            "key": "field_5cbf1ab891522",
                            "label": "Image",
                            "name": "image",
                            "type": "image",
                            "instructions": "Portrait: 700px by 800px\r\nLandscape: 800px by 700px\r\nSquare: 800px by 800px",
                            "required": 0,
                            "conditional_logic": 0,
                            "wrapper": {
                                "width": "50",
                                "class": "",
                                "id": ""
                            },
                            "return_format": "id",
                            "preview_size": "thumbnail",
                            "library": "all",
                            "min_width": "",
                            "min_height": "",
                            "min_size": "",
                            "max_width": "",
                            "max_height": "",
                            "max_size": "",
                            "mime_types": ""
                        },
                        {
                            "key": "field_5cbf1b2c91524",
                            "label": "Image Position",
                            "name": "image_position",
                            "type": "radio",
                            "instructions": "",
                            "required": 0,
                            "conditional_logic": 0,
                            "wrapper": {
                                "width": "25",
                                "class": "",
                                "id": ""
                            },
                            "choices": {
                                "left": "Left",
                                "right": "Right"
                            },
                            "allow_null": 0,
                            "other_choice": 0,
                            "default_value": "left",
                            "layout": "vertical",
                            "return_format": "value",
                            "save_other_choice": 0
                        },
                        {
                            "key": "field_5d307167a671e",
                            "label": "Image Crop",
                            "name": "image_crop",
                            "type": "radio",
                            "instructions": "",
                            "required": 0,
                            "conditional_logic": 0,
                            "wrapper": {
                                "width": "25",
                                "class": "",
                                "id": ""
                            },
                            "choices": {
                                "landscape": "Landscape",
                                "portrait": "Portrait",
                                "square": "Square"
                            },
                            "allow_null": 0,
                            "other_choice": 0,
                            "default_value": "landscape",
                            "layout": "vertical",
                            "return_format": "value",
                            "save_other_choice": 0
                        }
                    ],
                    "min": "",
                    "max": ""
                },
                "layout_5ceff97679985": {
                    "key": "layout_5ceff97679985",
                    "name": "block_feature_intro",
                    "label": "Feature Block (Intro)",
                    "display": "block",
                    "sub_fields": [
                        {
                            "key": "field_5ceff97679988",
                            "label": "Image",
                            "name": "image",
                            "type": "image",
                            "instructions": "Image will be cropped to square. Recommended size 800px x 800px.",
                            "required": 0,
                            "conditional_logic": 0,
                            "wrapper": {
                                "width": "50",
                                "class": "",
                                "id": ""
                            },
                            "return_format": "id",
                            "preview_size": "thumbnail",
                            "library": "all",
                            "min_width": "",
                            "min_height": "",
                            "min_size": "",
                            "max_width": "",
                            "max_height": "",
                            "max_size": "",
                            "mime_types": ""
                        },
                        {
                            "key": "field_5ceff97679986",
                            "label": "Content",
                            "name": "content",
                            "type": "wysiwyg",
                            "instructions": "",
                            "required": 0,
                            "conditional_logic": 0,
                            "wrapper": {
                                "width": "",
                                "class": "",
                                "id": ""
                            },
                            "default_value": "",
                            "tabs": "all",
                            "toolbar": "full",
                            "media_upload": 1,
                            "delay": 0
                        },
                        {
                            "key": "field_5ceff97679987",
                            "label": "Link",
                            "name": "link",
                            "type": "link",
                            "instructions": "",
                            "required": 0,
                            "conditional_logic": 0,
                            "wrapper": {
                                "width": "",
                                "class": "",
                                "id": ""
                            },
                            "return_format": "array"
                        }
                    ],
                    "min": "",
                    "max": ""
                },
                "layout_5cc82e6c13ec7": {
                    "key": "layout_5cc82e6c13ec7",
                    "name": "block_text_map",
                    "label": "Text with Map Block",
                    "display": "block",
                    "sub_fields": [
                        {
                            "key": "field_5cc82e6c13eca",
                            "label": "Map Text",
                            "name": "map_text",
                            "type": "textarea",
                            "instructions": "",
                            "required": 0,
                            "conditional_logic": 0,
                            "wrapper": {
                                "width": "50",
                                "class": "",
                                "id": ""
                            },
                            "default_value": "",
                            "placeholder": "",
                            "maxlength": "",
                            "rows": 2,
                            "new_lines": ""
                        },
                        {
                            "key": "field_5cc82e6c13ecb",
                            "label": "Map Position",
                            "name": "map_position",
                            "type": "radio",
                            "instructions": "",
                            "required": 0,
                            "conditional_logic": 0,
                            "wrapper": {
                                "width": "50",
                                "class": "",
                                "id": ""
                            },
                            "choices": {
                                "left": "Left",
                                "right": "Right"
                            },
                            "allow_null": 0,
                            "other_choice": 0,
                            "default_value": "left",
                            "layout": "vertical",
                            "return_format": "value",
                            "save_other_choice": 0
                        },
                        {
                            "key": "field_5cc82e6c13ec8",
                            "label": "Content",
                            "name": "content",
                            "type": "wysiwyg",
                            "instructions": "",
                            "required": 0,
                            "conditional_logic": 0,
                            "wrapper": {
                                "width": "",
                                "class": "",
                                "id": ""
                            },
                            "default_value": "",
                            "tabs": "all",
                            "toolbar": "full",
                            "media_upload": 1,
                            "delay": 0
                        },
                        {
                            "key": "field_5cc82e6c13ec9",
                            "label": "Link",
                            "name": "link",
                            "type": "link",
                            "instructions": "",
                            "required": 0,
                            "conditional_logic": 0,
                            "wrapper": {
                                "width": "",
                                "class": "",
                                "id": ""
                            },
                            "return_format": "array"
                        }
                    ],
                    "min": "",
                    "max": ""
                },
                "layout_5cc8761b426d2": {
                    "key": "layout_5cc8761b426d2",
                    "name": "block_text_satellite",
                    "label": "Text with Satellite Map Block",
                    "display": "block",
                    "sub_fields": [
                        {
                            "key": "field_5cc8761b426d5",
                            "label": "Map Text",
                            "name": "map_text",
                            "type": "textarea",
                            "instructions": "",
                            "required": 0,
                            "conditional_logic": 0,
                            "wrapper": {
                                "width": "50",
                                "class": "",
                                "id": ""
                            },
                            "default_value": "il laghetto di greppi cupi",
                            "placeholder": "",
                            "maxlength": "",
                            "rows": 2,
                            "new_lines": ""
                        },
                        {
                            "key": "field_5cc8761b426d3",
                            "label": "Content",
                            "name": "content",
                            "type": "wysiwyg",
                            "instructions": "",
                            "required": 0,
                            "conditional_logic": 0,
                            "wrapper": {
                                "width": "",
                                "class": "",
                                "id": ""
                            },
                            "default_value": "",
                            "tabs": "all",
                            "toolbar": "full",
                            "media_upload": 1,
                            "delay": 0
                        },
                        {
                            "key": "field_5cc8761b426d4",
                            "label": "Link",
                            "name": "link",
                            "type": "link",
                            "instructions": "",
                            "required": 0,
                            "conditional_logic": 0,
                            "wrapper": {
                                "width": "",
                                "class": "",
                                "id": ""
                            },
                            "return_format": "array"
                        }
                    ],
                    "min": "",
                    "max": ""
                },
                "layout_5cc85c24eed81": {
                    "key": "layout_5cc85c24eed81",
                    "name": "block_talk_to_us",
                    "label": "Talk To Us Block",
                    "display": "block",
                    "sub_fields": [
                        {
                            "key": "field_5cc85c6cb03b1",
                            "label": "Heading",
                            "name": "heading",
                            "type": "text",
                            "instructions": "",
                            "required": 0,
                            "conditional_logic": 0,
                            "wrapper": {
                                "width": "",
                                "class": "",
                                "id": ""
                            },
                            "default_value": "Talk To Us",
                            "placeholder": "",
                            "prepend": "",
                            "append": "",
                            "maxlength": ""
                        },
                        {
                            "key": "field_5cc85c34eed82",
                            "label": "",
                            "name": "",
                            "type": "message",
                            "instructions": "",
                            "required": 0,
                            "conditional_logic": 0,
                            "wrapper": {
                                "width": "",
                                "class": "",
                                "id": ""
                            },
                            "message": "This block automatically pulls through the contact details. To edit the contact details, go to Website Settings > Contact Details",
                            "new_lines": "",
                            "esc_html": 0
                        }
                    ],
                    "min": "",
                    "max": ""
                },
                "layout_5cc6fbea756a5": {
                    "key": "layout_5cc6fbea756a5",
                    "name": "block_hero",
                    "label": "Hero Block",
                    "display": "block",
                    "sub_fields": [
                        {
                            "key": "field_5cc6fbea756a8",
                            "label": "Image",
                            "name": "image",
                            "type": "image",
                            "instructions": "Recommended image size: 1920px by 1920px",
                            "required": 0,
                            "conditional_logic": 0,
                            "wrapper": {
                                "width": "50",
                                "class": "",
                                "id": ""
                            },
                            "return_format": "id",
                            "preview_size": "thumbnail",
                            "library": "all",
                            "min_width": "",
                            "min_height": "",
                            "min_size": "",
                            "max_width": "",
                            "max_height": "",
                            "max_size": "",
                            "mime_types": ""
                        },
                        {
                            "key": "field_5cc6fbea756a6",
                            "label": "Content",
                            "name": "content",
                            "type": "wysiwyg",
                            "instructions": "",
                            "required": 0,
                            "conditional_logic": 0,
                            "wrapper": {
                                "width": "",
                                "class": "",
                                "id": ""
                            },
                            "default_value": "",
                            "tabs": "all",
                            "toolbar": "full",
                            "media_upload": 1,
                            "delay": 0
                        },
                        {
                            "key": "field_5cc720e5b53d7",
                            "label": "Style",
                            "name": "style",
                            "type": "radio",
                            "instructions": "This controls the white shapes around the block.",
                            "required": 1,
                            "conditional_logic": 0,
                            "wrapper": {
                                "width": "50",
                                "class": "",
                                "id": ""
                            },
                            "choices": {
                                "style-1": "Style 1",
                                "style-2": "Style 2"
                            },
                            "allow_null": 0,
                            "other_choice": 0,
                            "default_value": "style-1",
                            "layout": "vertical",
                            "return_format": "value",
                            "save_other_choice": 0
                        },
                        {
                            "key": "field_5d305fca095b2",
                            "label": "Text Colour",
                            "name": "text_color",
                            "type": "select",
                            "instructions": "",
                            "required": 0,
                            "conditional_logic": 0,
                            "wrapper": {
                                "width": "50",
                                "class": "",
                                "id": ""
                            },
                            "choices": {
                                "white": "White",
                                "black": "Black"
                            },
                            "default_value": [
                                "white"
                            ],
                            "allow_null": 0,
                            "multiple": 0,
                            "ui": 0,
                            "return_format": "value",
                            "ajax": 0,
                            "placeholder": ""
                        },
                        {
                            "key": "field_5cc6fbea756a7",
                            "label": "Link",
                            "name": "link",
                            "type": "link",
                            "instructions": "",
                            "required": 0,
                            "conditional_logic": 0,
                            "wrapper": {
                                "width": "",
                                "class": "",
                                "id": ""
                            },
                            "return_format": ""
                        }
                    ],
                    "min": "",
                    "max": ""
                },
                "layout_5cc6fb2b7569e": {
                    "key": "layout_5cc6fb2b7569e",
                    "name": "block_annotated_image",
                    "label": "Annotated Image Block",
                    "display": "block",
                    "sub_fields": [
                        {
                            "key": "field_5cc6fb57756a4",
                            "label": "Right Caption",
                            "name": "right_caption",
                            "type": "wysiwyg",
                            "instructions": "",
                            "required": 0,
                            "conditional_logic": 0,
                            "wrapper": {
                                "width": "50",
                                "class": "",
                                "id": ""
                            },
                            "default_value": "",
                            "tabs": "all",
                            "toolbar": "full",
                            "media_upload": 0,
                            "delay": 0
                        },
                        {
                            "key": "field_5cc6fb2b756a0",
                            "label": "Link",
                            "name": "link",
                            "type": "link",
                            "instructions": "",
                            "required": 0,
                            "conditional_logic": 0,
                            "wrapper": {
                                "width": "",
                                "class": "",
                                "id": ""
                            },
                            "return_format": "array"
                        },
                        {
                            "key": "field_5cc6fb2b756a1",
                            "label": "Image",
                            "name": "image",
                            "type": "image",
                            "instructions": "Image can have any dimensions; will resize according to the image's aspect ratio.",
                            "required": 1,
                            "conditional_logic": 0,
                            "wrapper": {
                                "width": "100",
                                "class": "",
                                "id": ""
                            },
                            "return_format": "id",
                            "preview_size": "thumbnail",
                            "library": "all",
                            "min_width": "",
                            "min_height": "",
                            "min_size": "",
                            "max_width": "",
                            "max_height": "",
                            "max_size": "",
                            "mime_types": ""
                        },
                        {
                            "key": "field_5cc6fb3d756a3",
                            "label": "Left Caption",
                            "name": "left_caption",
                            "type": "wysiwyg",
                            "instructions": "",
                            "required": 0,
                            "conditional_logic": 0,
                            "wrapper": {
                                "width": "50",
                                "class": "",
                                "id": ""
                            },
                            "default_value": "",
                            "tabs": "all",
                            "toolbar": "full",
                            "media_upload": 0,
                            "delay": 0
                        }
                    ],
                    "min": "",
                    "max": ""
                },
                "layout_5cc6d7467e436": {
                    "key": "layout_5cc6d7467e436",
                    "name": "block_products",
                    "label": "Products Block",
                    "display": "block",
                    "sub_fields": [
                        {
                            "key": "field_5cc6d7597e43b",
                            "label": "Products",
                            "name": "products",
                            "type": "post_object",
                            "instructions": "Select up to 2 products",
                            "required": 0,
                            "conditional_logic": 0,
                            "wrapper": {
                                "width": "",
                                "class": "",
                                "id": ""
                            },
                            "post_type": [
                                "product"
                            ],
                            "taxonomy": "",
                            "allow_null": 0,
                            "multiple": 1,
                            "return_format": "object",
                            "ui": 1
                        },
                        {
                            "key": "field_5cc6d7467e437",
                            "label": "Content",
                            "name": "content",
                            "type": "wysiwyg",
                            "instructions": "",
                            "required": 0,
                            "conditional_logic": 0,
                            "wrapper": {
                                "width": "",
                                "class": "",
                                "id": ""
                            },
                            "default_value": "",
                            "tabs": "all",
                            "toolbar": "full",
                            "media_upload": 1,
                            "delay": 0
                        },
                        {
                            "key": "field_5cc6d7467e438",
                            "label": "Link",
                            "name": "link",
                            "type": "link",
                            "instructions": "",
                            "required": 0,
                            "conditional_logic": 0,
                            "wrapper": {
                                "width": "",
                                "class": "",
                                "id": ""
                            },
                            "return_format": "array"
                        }
                    ],
                    "min": "",
                    "max": ""
                },
                "layout_5d00df15f9bc0": {
                    "key": "layout_5d00df15f9bc0",
                    "name": "block_video",
                    "label": "Video Block",
                    "display": "block",
                    "sub_fields": [
                        {
                            "key": "field_5d00df4ff9bc4",
                            "label": "Text position",
                            "name": "text_position",
                            "type": "radio",
                            "instructions": "",
                            "required": 0,
                            "conditional_logic": 0,
                            "wrapper": {
                                "width": "",
                                "class": "",
                                "id": ""
                            },
                            "choices": {
                                "left": "Left",
                                "right": "Right"
                            },
                            "allow_null": 0,
                            "other_choice": 0,
                            "default_value": "",
                            "layout": "vertical",
                            "return_format": "value",
                            "save_other_choice": 0
                        },
                        {
                            "key": "field_5d00df15f9bc3",
                            "label": "Video",
                            "name": "video",
                            "type": "file",
                            "instructions": "Mp4 video (up to 6MB)",
                            "required": 0,
                            "conditional_logic": 0,
                            "wrapper": {
                                "width": "",
                                "class": "",
                                "id": ""
                            },
                            "return_format": "array",
                            "library": "all",
                            "min_size": "",
                            "max_size": 6,
                            "mime_types": "mp4"
                        },
                        {
                            "key": "field_5d00df15f9bc1",
                            "label": "Content",
                            "name": "content",
                            "type": "wysiwyg",
                            "instructions": "",
                            "required": 0,
                            "conditional_logic": 0,
                            "wrapper": {
                                "width": "",
                                "class": "",
                                "id": ""
                            },
                            "default_value": "",
                            "tabs": "all",
                            "toolbar": "full",
                            "media_upload": 1,
                            "delay": 0
                        },
                        {
                            "key": "field_5d00df15f9bc2",
                            "label": "Link",
                            "name": "link",
                            "type": "link",
                            "instructions": "",
                            "required": 0,
                            "conditional_logic": 0,
                            "wrapper": {
                                "width": "",
                                "class": "",
                                "id": ""
                            },
                            "return_format": "array"
                        }
                    ],
                    "min": "",
                    "max": ""
                },
                "layout_5cbf23ffa448f": {
                    "key": "layout_5cbf23ffa448f",
                    "name": "block_full_width_content",
                    "label": "Full Width Content",
                    "display": "block",
                    "sub_fields": [
                        {
                            "key": "field_5cbf2408a4490",
                            "label": "Content",
                            "name": "content",
                            "type": "wysiwyg",
                            "instructions": "",
                            "required": 1,
                            "conditional_logic": 0,
                            "wrapper": {
                                "width": "",
                                "class": "",
                                "id": ""
                            },
                            "default_value": "",
                            "tabs": "all",
                            "toolbar": "full",
                            "media_upload": 1,
                            "delay": 0
                        }
                    ],
                    "min": "",
                    "max": ""
                },
                "layout_5cbf2419a4491": {
                    "key": "layout_5cbf2419a4491",
                    "name": "block_two_column_content",
                    "label": "Two Column Content",
                    "display": "block",
                    "sub_fields": [
                        {
                            "key": "field_5cbf2438a4493",
                            "label": "2nd Column Content",
                            "name": "content_2",
                            "type": "wysiwyg",
                            "instructions": "",
                            "required": 0,
                            "conditional_logic": 0,
                            "wrapper": {
                                "width": "50",
                                "class": "",
                                "id": ""
                            },
                            "default_value": "",
                            "tabs": "all",
                            "toolbar": "full",
                            "media_upload": 1,
                            "delay": 0
                        },
                        {
                            "key": "field_5cbf2572a4495",
                            "label": "Heading",
                            "name": "heading",
                            "type": "text",
                            "instructions": "",
                            "required": 0,
                            "conditional_logic": 0,
                            "wrapper": {
                                "width": "",
                                "class": "",
                                "id": ""
                            },
                            "default_value": "",
                            "placeholder": "",
                            "prepend": "",
                            "append": "",
                            "maxlength": ""
                        },
                        {
                            "key": "field_5cbf242aa4492",
                            "label": "1st Column Content",
                            "name": "content",
                            "type": "wysiwyg",
                            "instructions": "",
                            "required": 0,
                            "conditional_logic": 0,
                            "wrapper": {
                                "width": "50",
                                "class": "",
                                "id": ""
                            },
                            "default_value": "",
                            "tabs": "all",
                            "toolbar": "full",
                            "media_upload": 1,
                            "delay": 0
                        }
                    ],
                    "min": "",
                    "max": ""
                },
                "layout_5cc6f3db58cc9": {
                    "key": "layout_5cc6f3db58cc9",
                    "name": "block_featured_text",
                    "label": "Featured Text \/ Quote Block",
                    "display": "block",
                    "sub_fields": [
                        {
                            "key": "field_5cc6f40258cce",
                            "label": "Source (optional)",
                            "name": "source",
                            "type": "text",
                            "instructions": "",
                            "required": 0,
                            "conditional_logic": 0,
                            "wrapper": {
                                "width": "",
                                "class": "",
                                "id": ""
                            },
                            "default_value": "",
                            "placeholder": "",
                            "prepend": "",
                            "append": "",
                            "maxlength": ""
                        },
                        {
                            "key": "field_5cc6f3f658ccd",
                            "label": "Text",
                            "name": "text",
                            "type": "textarea",
                            "instructions": "Text for blockquote",
                            "required": 1,
                            "conditional_logic": 0,
                            "wrapper": {
                                "width": "70",
                                "class": "",
                                "id": ""
                            },
                            "default_value": "",
                            "placeholder": "",
                            "maxlength": "",
                            "rows": 4,
                            "new_lines": ""
                        },
                        {
                            "key": "field_5cc6f4eefc3c7",
                            "label": "Align Text",
                            "name": "align",
                            "type": "radio",
                            "instructions": "",
                            "required": 0,
                            "conditional_logic": 0,
                            "wrapper": {
                                "width": "30",
                                "class": "",
                                "id": ""
                            },
                            "choices": {
                                "center": "Center",
                                "left": "Left",
                                "right": "Right"
                            },
                            "allow_null": 0,
                            "other_choice": 0,
                            "default_value": "center",
                            "layout": "vertical",
                            "return_format": "value",
                            "save_other_choice": 0
                        }
                    ],
                    "min": "",
                    "max": ""
                },
                "layout_5cbf2532a4494": {
                    "key": "layout_5cbf2532a4494",
                    "name": "block_latest_news",
                    "label": "Latest News Block",
                    "display": "block",
                    "sub_fields": [
                        {
                            "key": "field_5cbf2686a4498",
                            "label": "Link",
                            "name": "link",
                            "type": "link",
                            "instructions": "",
                            "required": 0,
                            "conditional_logic": 0,
                            "wrapper": {
                                "width": "",
                                "class": "",
                                "id": ""
                            },
                            "return_format": "array"
                        },
                        {
                            "key": "field_5cbf2682a4497",
                            "label": "Heading",
                            "name": "heading",
                            "type": "text",
                            "instructions": "",
                            "required": 0,
                            "conditional_logic": 0,
                            "wrapper": {
                                "width": "",
                                "class": "",
                                "id": ""
                            },
                            "default_value": "",
                            "placeholder": "",
                            "prepend": "",
                            "append": "",
                            "maxlength": ""
                        },
                        {
                            "key": "field_5cbf265fa4496",
                            "label": "",
                            "name": "",
                            "type": "message",
                            "instructions": "",
                            "required": 0,
                            "conditional_logic": 0,
                            "wrapper": {
                                "width": "",
                                "class": "",
                                "id": ""
                            },
                            "message": "This block will automatically pull through the latest news posts.",
                            "new_lines": "wpautop",
                            "esc_html": 0
                        }
                    ],
                    "min": "",
                    "max": ""
                },
                "layout_5cbf29a35ce0f": {
                    "key": "layout_5cbf29a35ce0f",
                    "name": "block_form",
                    "label": "Form Block",
                    "display": "block",
                    "sub_fields": [
                        {
                            "key": "field_5cbf29ab5ce10",
                            "label": "Heading",
                            "name": "heading",
                            "type": "text",
                            "instructions": "",
                            "required": 0,
                            "conditional_logic": 0,
                            "wrapper": {
                                "width": "",
                                "class": "",
                                "id": ""
                            },
                            "default_value": "",
                            "placeholder": "",
                            "prepend": "",
                            "append": "",
                            "maxlength": ""
                        },
                        {
                            "key": "field_5cbf29f65ce11",
                            "label": "Form",
                            "name": "form_id",
                            "type": "select",
                            "instructions": "Select which form you want to show in this block.",
                            "required": 1,
                            "conditional_logic": 0,
                            "wrapper": {
                                "width": "",
                                "class": "",
                                "id": ""
                            },
                            "choices": {
                                "contact": "Contact",
                                "newsletter-signup": "Newsletter signup",
                                "club-signup": "Club signup"
                            },
                            "default_value": [],
                            "allow_null": 0,
                            "multiple": 0,
                            "ui": 0,
                            "return_format": "value",
                            "ajax": 0,
                            "placeholder": ""
                        }
                    ],
                    "min": "",
                    "max": ""
                },
                "layout_5cc80d4522b1e": {
                    "key": "layout_5cc80d4522b1e",
                    "name": "block_instagram",
                    "label": "Instagram Block",
                    "display": "block",
                    "sub_fields": [
                        {
                            "key": "field_5cc80d4b22b1f",
                            "label": "",
                            "name": "",
                            "type": "message",
                            "instructions": "",
                            "required": 0,
                            "conditional_logic": 0,
                            "wrapper": {
                                "width": "",
                                "class": "",
                                "id": ""
                            },
                            "message": "This block pulls through the Instagram feed on to the page",
                            "new_lines": "",
                            "esc_html": 0
                        }
                    ],
                    "min": "",
                    "max": ""
                }
            },
            "button_label": "Add Block",
            "min": "",
            "max": ""
        }
    ],
    "location": [
        [
            {
                "param": "post_type",
                "operator": "==",
                "value": "page"
            }
        ],
        [
            {
                "param": "post_type",
                "operator": "==",
                "value": "post"
            }
        ]
    ],
    "menu_order": 20,
    "position": "normal",
    "style": "default",
    "label_placement": "top",
    "instruction_placement": "label",
    "hide_on_screen": "",
    "active": 1,
    "description": "",
    "modified": 1608161613
}